data_go_mcp/pps_narajangteo/__init__.py
data_go_mcp/pps_narajangteo/api_client.py
data_go_mcp/pps_narajangteo/models.py
data_go_mcp/pps_narajangteo/server.py
data_go_mcp_pps_narajangteo-0.1.1.dist-info/METADATA
data_go_mcp_pps_narajangteo-0.1.1.dist-info/WHEEL
data_go_mcp_pps_narajangteo-0.1.1.dist-info/entry_points.txt
data_go_mcp_pps_narajangteo-0.1.1.dist-info/licenses/LICENSE
data_go_mcp_pps_narajangteo-0.1.1.dist-info/RECORD
