Metadata-Version: 2.4
Name: data-go-mcp.pps-narajangteo
Version: 0.1.1
Summary: MCP server for 나라장터 공공데이터개방표준서비스 (Public Procurement Service Open Data Standard)
Project-URL: Homepage, https://github.com/yourusername/data-go-mcp-servers
Project-URL: Repository, https://github.com/yourusername/data-go-mcp-servers
Project-URL: Documentation, https://github.com/yourusername/data-go-mcp-servers/tree/main/src/pps-narajangteo
Project-URL: Bug Tracker, https://github.com/yourusername/data-go-mcp-servers/issues
Project-URL: Changelog, https://github.com/yourusername/data-go-mcp-servers/blob/main/src/pps-narajangteo/CHANGELOG.md
Author: DataGo MCP
License: Apache-2.0
License-File: LICENSE
Keywords: api,data.go.kr,korea,mcp,pps-narajangteo
Classifier: Development Status :: 3 - Alpha
Classifier: Intended Audience :: Developers
Classifier: License :: OSI Approved :: Apache Software License
Classifier: Programming Language :: Python :: 3
Classifier: Programming Language :: Python :: 3.10
Classifier: Programming Language :: Python :: 3.11
Classifier: Programming Language :: Python :: 3.12
Classifier: Programming Language :: Python :: 3.13
Requires-Python: >=3.10
Requires-Dist: httpx>=0.28.1
Requires-Dist: mcp[cli]>=1.13.0
Requires-Dist: pydantic>=2.11.7
Requires-Dist: python-dotenv>=1.1.1
Requires-Dist: xmltodict>=0.14.2
